{
	"state": "ok",
	"left_bg": {
				"basic_url":"http://lendfating.github.com/assets/images/left-bg/",
				"size": "50"
			},
	"phrase": [
				"最好的青春，当做最有意义的事情，切莫虚度了此时，后悔了明日。",
				"在生活中思考，在嘈杂中沉静，在实践中学习",
				"生如夏花之绚烂，死如秋叶之静美.",
				"千淘万漉虽辛苦，吹尽狂沙始到金。",
				"业精于勤，荒于嬉；行成于思，毁于随。",
				"非淡泊无以明志，非宁静无以致远。",
				"阳春之曲，和者必寡；盛名之下，其实难副。",
				"木秀于林，风必摧之。",
				"海纳百川，有容乃大；壁立千仞，无欲则刚。",
				"山高自有客行路，水深自有渡船人。"
			],
	"categories":{
		"定期总结": { "avatar":"http://lendfating.github.com/assets/images/categories/定期总结.jpg", "description":"有反馈才会权衡得失" },
		"定期规划": { "avatar":"http://lendfating.github.com/assets/images/categories/定期规划.jpg", "description":"有目标才会更有动力" },
		"异想天开": { "avatar":"http://lendfating.github.com/assets/images/categories/异想天开.jpg", "description":"未来不可知，但是或许可预" },
		"生活点滴": { "avatar":"http://lendfating.github.com/assets/images/categories/生活点滴.jpg", "description":"繁杂的或许就是生活" }
	}
}